changelog/__init__.py
changelog/changelog_generator.py
changelog/footer.py
changelog/generate.py
changelog/gitrepo.py
changelog/header.py
python_changelog-0.3.3.dist-info/LICENCE
python_changelog-0.3.3.dist-info/METADATA
python_changelog-0.3.3.dist-info/WHEEL
python_changelog-0.3.3.dist-info/entry_points.txt
python_changelog-0.3.3.dist-info/top_level.txt
python_changelog-0.3.3.dist-info/RECORD
