Metadata-Version: 2.1
Name: python-changelog
Version: 0.3.3
Summary: A module that generates changelogs based on git tags.
Author: Lennart Suwe
Author-email: lennsa999@gmx.de
License: UNKNOWN
Keywords: changelog conventional commit git
Platform: UNKNOWN
License-File: LICENCE
Requires-Dist: Click (<7.1)
Requires-Dist: GitPython (<3.2)
Requires-Dist: requests
